{
 "title": "Henry VI, part 3", 
 "acts": [
  [
   {
    "total_lines": 286, 
    "deg_assort_coeff": -0.17239103638755598, 
    "density": 0.38461538461538464, 
    "scene": "1", 
    "total_degrees": 30, 
    "avg_shortest_path": 1.705128205128205, 
    "location": "London. The Parliament-house.", 
    "act": "1", 
    "graph_img_f": "imgs/3henryvi_1_1.png", 
    "char_data": {
     "PRINCE EDWARD": {
      "ratio": 2.0, 
      "degrees": 2, 
      "nlines": 4
     }, 
     "NORFOLK": {
      "ratio": 0.75, 
      "degrees": 4, 
      "nlines": 3
     }, 
     "RICHARD": {
      "ratio": 1.17, 
      "degrees": 6, 
      "nlines": 7
     }, 
     "KING HENRY VI": {
      "ratio": 7.6, 
      "degrees": 10, 
      "nlines": 76
     }, 
     "QUEEN MARGARET": {
      "ratio": 21.5, 
      "degrees": 2, 
      "nlines": 43
     }, 
     "NORTHUMBERLAND": {
      "ratio": 3.25, 
      "degrees": 4, 
      "nlines": 13
     }, 
     "CLIFFORD": {
      "ratio": 4.75, 
      "degrees": 4, 
      "nlines": 19
     }, 
     "MONTAGUE": {
      "ratio": 1.5, 
      "degrees": 4, 
      "nlines": 6
     }, 
     "EDWARD": {
      "ratio": 1.67, 
      "degrees": 3, 
      "nlines": 5
     }, 
     "YORK": {
      "ratio": 6.33, 
      "degrees": 6, 
      "nlines": 38
     }, 
     "WARWICK": {
      "ratio": 5.88, 
      "degrees": 8, 
      "nlines": 47
     }, 
     "EXETER": {
      "ratio": 4.67, 
      "degrees": 3, 
      "nlines": 14
     }, 
     "WESTMORELAND": {
      "ratio": 2.75, 
      "degrees": 4, 
      "nlines": 11
     }
    }, 
    "avg_clustering": 0.7476800976800977
   }, 
   {
    "total_lines": 81, 
    "deg_assort_coeff": -0.34969966048576651, 
    "density": 0.5333333333333333, 
    "scene": "2", 
    "total_degrees": 8, 
    "avg_shortest_path": 1.4666666666666666, 
    "location": "Sandal Castle.", 
    "act": "1", 
    "graph_img_f": "imgs/3henryvi_1_2.png", 
    "char_data": {
     "RICHARD": {
      "ratio": 11.0, 
      "degrees": 2, 
      "nlines": 22
     }, 
     "MONTAGUE": {
      "ratio": 3.0, 
      "degrees": 3, 
      "nlines": 9
     }, 
     "EDWARD": {
      "ratio": 3.0, 
      "degrees": 3, 
      "nlines": 9
     }, 
     "Messenger": {
      "ratio": 4.0, 
      "degrees": 1, 
      "nlines": 4
     }, 
     "YORK": {
      "ratio": 7.2, 
      "degrees": 5, 
      "nlines": 36
     }, 
     "JOHN MORTIMER": {
      "ratio": 0.5, 
      "degrees": 2, 
      "nlines": 1
     }
    }, 
    "avg_clustering": 0.6055555555555555
   }, 
   {
    "total_lines": 59, 
    "deg_assort_coeff": -0.64079822616407978, 
    "density": 0.6666666666666666, 
    "scene": "3", 
    "total_degrees": 2, 
    "avg_shortest_path": 1.3333333333333333, 
    "location": "Field of battle betwixt Sandal Castle and Wakefield.", 
    "act": "1", 
    "graph_img_f": "imgs/3henryvi_1_3.png", 
    "char_data": {
     "RUTLAND": {
      "ratio": 26.0, 
      "degrees": 1, 
      "nlines": 26
     }, 
     "CLIFFORD": {
      "ratio": 14.5, 
      "degrees": 2, 
      "nlines": 29
     }, 
     "Tutor": {
      "ratio": 4.0, 
      "degrees": 1, 
      "nlines": 4
     }
    }, 
    "avg_clustering": 0.0
   }, 
   {
    "total_lines": 189, 
    "deg_assort_coeff": -0.33333333333330017, 
    "density": 1.0, 
    "scene": "4", 
    "total_degrees": 6, 
    "avg_shortest_path": 1.0, 
    "location": "Another part of the field.", 
    "act": "1", 
    "graph_img_f": "imgs/3henryvi_1_4.png", 
    "char_data": {
     "QUEEN MARGARET": {
      "ratio": 18.67, 
      "degrees": 3, 
      "nlines": 56
     }, 
     "NORTHUMBERLAND": {
      "ratio": 5.33, 
      "degrees": 3, 
      "nlines": 16
     }, 
     "YORK": {
      "ratio": 34.33, 
      "degrees": 3, 
      "nlines": 103
     }, 
     "CLIFFORD": {
      "ratio": 4.67, 
      "degrees": 3, 
      "nlines": 14
     }
    }, 
    "avg_clustering": 1.0
   }
  ], 
  [
   {
    "total_lines": 213, 
    "deg_assort_coeff": -0.33333333333333359, 
    "density": 1.0, 
    "scene": "1", 
    "total_degrees": 6, 
    "avg_shortest_path": 1.0, 
    "location": "A plain near Mortimer's Cross in Herefordshire.", 
    "act": "2", 
    "graph_img_f": "imgs/3henryvi_2_1.png", 
    "char_data": {
     "EDWARD": {
      "ratio": 13.67, 
      "degrees": 3, 
      "nlines": 41
     }, 
     "Messenger": {
      "ratio": 8.0, 
      "degrees": 3, 
      "nlines": 24
     }, 
     "RICHARD": {
      "ratio": 22.33, 
      "degrees": 3, 
      "nlines": 67
     }, 
     "WARWICK": {
      "ratio": 27.0, 
      "degrees": 3, 
      "nlines": 81
     }
    }, 
    "avg_clustering": 1.0
   }, 
   {
    "total_lines": 180, 
    "deg_assort_coeff": -0.10198321775943088, 
    "density": 0.43636363636363634, 
    "scene": "2", 
    "total_degrees": 24, 
    "avg_shortest_path": 1.690909090909091, 
    "location": "Before York.", 
    "act": "2", 
    "graph_img_f": "imgs/3henryvi_2_2.png", 
    "char_data": {
     "PRINCE EDWARD": {
      "ratio": 1.5, 
      "degrees": 4, 
      "nlines": 6
     }, 
     "RICHARD": {
      "ratio": 2.86, 
      "degrees": 7, 
      "nlines": 20
     }, 
     "KING HENRY VI": {
      "ratio": 4.6, 
      "degrees": 5, 
      "nlines": 23
     }, 
     "QUEEN MARGARET": {
      "ratio": 4.4, 
      "degrees": 5, 
      "nlines": 22
     }, 
     "NORTHUMBERLAND": {
      "ratio": 0.5, 
      "degrees": 4, 
      "nlines": 2
     }, 
     "PRINCE": {
      "ratio": 1.5, 
      "degrees": 2, 
      "nlines": 3
     }, 
     "EDWARD": {
      "ratio": 6.5, 
      "degrees": 6, 
      "nlines": 39
     }, 
     "Messenger": {
      "ratio": 6.0, 
      "degrees": 1, 
      "nlines": 6
     }, 
     "WARWICK": {
      "ratio": 0.83, 
      "degrees": 6, 
      "nlines": 5
     }, 
     "GEORGE": {
      "ratio": 7.0, 
      "degrees": 1, 
      "nlines": 7
     }, 
     "CLIFFORD": {
      "ratio": 6.71, 
      "degrees": 7, 
      "nlines": 47
     }
    }, 
    "avg_clustering": 0.5497835497835498
   }, 
   {
    "total_lines": 60, 
    "deg_assort_coeff": -0.6182572614107904, 
    "density": 0.8333333333333334, 
    "scene": "3", 
    "total_degrees": 5, 
    "avg_shortest_path": 1.1666666666666667, 
    "location": "A field of battle between Towton and Saxton, in", 
    "act": "2", 
    "graph_img_f": "imgs/3henryvi_2_3.png", 
    "char_data": {
     "EDWARD": {
      "ratio": 5.33, 
      "degrees": 3, 
      "nlines": 16
     }, 
     "GEORGE": {
      "ratio": 6.0, 
      "degrees": 2, 
      "nlines": 12
     }, 
     "RICHARD": {
      "ratio": 6.5, 
      "degrees": 2, 
      "nlines": 13
     }, 
     "WARWICK": {
      "ratio": 6.33, 
      "degrees": 3, 
      "nlines": 19
     }
    }, 
    "avg_clustering": 0.8333333333333333
   }, 
   {
    "total_lines": 15, 
    "deg_assort_coeff": -1, 
    "density": 1.0, 
    "scene": "4", 
    "total_degrees": 1, 
    "avg_shortest_path": 1.0, 
    "location": "Another part of the field.", 
    "act": "2", 
    "graph_img_f": "imgs/3henryvi_2_4.png", 
    "char_data": {
     "RICHARD": {
      "ratio": 7.0, 
      "degrees": 1, 
      "nlines": 7
     }, 
     "CLIFFORD": {
      "ratio": 8.0, 
      "degrees": 1, 
      "nlines": 8
     }
    }, 
    "avg_clustering": 0.0
   }, 
   {
    "total_lines": 145, 
    "deg_assort_coeff": 0.077272727272727007, 
    "density": 0.4666666666666667, 
    "scene": "5", 
    "total_degrees": 7, 
    "avg_shortest_path": 1.6666666666666667, 
    "location": "Another part of the field.", 
    "act": "2", 
    "graph_img_f": "imgs/3henryvi_2_5.png", 
    "char_data": {
     "PRINCE EDWARD": {
      "ratio": 1.5, 
      "degrees": 2, 
      "nlines": 3
     }, 
     "KING HENRY VI": {
      "ratio": 20.5, 
      "degrees": 4, 
      "nlines": 82
     }, 
     "QUEEN MARGARET": {
      "ratio": 3.0, 
      "degrees": 2, 
      "nlines": 6
     }, 
     "Father": {
      "ratio": 14.0, 
      "degrees": 2, 
      "nlines": 28
     }, 
     "Son": {
      "ratio": 11.5, 
      "degrees": 2, 
      "nlines": 23
     }, 
     "EXETER": {
      "ratio": 1.5, 
      "degrees": 2, 
      "nlines": 3
     }
    }, 
    "avg_clustering": 0.36111111111111116
   }, 
   {
    "total_lines": 115, 
    "deg_assort_coeff": -0.39359267734554004, 
    "density": 0.7, 
    "scene": "6", 
    "total_degrees": 7, 
    "avg_shortest_path": 1.3, 
    "location": "Another part of the field.", 
    "act": "2", 
    "graph_img_f": "imgs/3henryvi_2_6.png", 
    "char_data": {
     "CLIFFORD": {
      "ratio": 32.0, 
      "degrees": 1, 
      "nlines": 32
     }, 
     "EDWARD": {
      "ratio": 5.75, 
      "degrees": 4, 
      "nlines": 23
     }, 
     "GEORGE": {
      "ratio": 1.0, 
      "degrees": 3, 
      "nlines": 3
     }, 
     "RICHARD": {
      "ratio": 8.0, 
      "degrees": 3, 
      "nlines": 24
     }, 
     "WARWICK": {
      "ratio": 11.0, 
      "degrees": 3, 
      "nlines": 33
     }
    }, 
    "avg_clustering": 0.7
   }
  ], 
  [
   {
    "total_lines": 103, 
    "deg_assort_coeff": -0.50000000000000255, 
    "density": 1.0, 
    "scene": "1", 
    "total_degrees": 3, 
    "avg_shortest_path": 1.0, 
    "location": "A forest in the north of England.", 
    "act": "3", 
    "graph_img_f": "imgs/3henryvi_3_1.png", 
    "char_data": {
     "First Keeper": {
      "ratio": 9.0, 
      "degrees": 2, 
      "nlines": 18
     }, 
     "Second Keeper": {
      "ratio": 7.5, 
      "degrees": 2, 
      "nlines": 15
     }, 
     "KING HENRY VI": {
      "ratio": 35.0, 
      "degrees": 2, 
      "nlines": 70
     }
    }, 
    "avg_clustering": 1.0
   }, 
   {
    "total_lines": 215, 
    "deg_assort_coeff": -0.5315821839585364, 
    "density": 0.7, 
    "scene": "2", 
    "total_degrees": 7, 
    "avg_shortest_path": 1.3, 
    "location": "London. The palace.", 
    "act": "3", 
    "graph_img_f": "imgs/3henryvi_3_2.png", 
    "char_data": {
     "LADY GREY": {
      "ratio": 12.0, 
      "degrees": 3, 
      "nlines": 36
     }, 
     "KING EDWARD IV": {
      "ratio": 14.75, 
      "degrees": 4, 
      "nlines": 59
     }, 
     "CLARENCE": {
      "ratio": 4.67, 
      "degrees": 3, 
      "nlines": 14
     }, 
     "Nobleman": {
      "ratio": 2.0, 
      "degrees": 1, 
      "nlines": 2
     }, 
     "GLOUCESTER": {
      "ratio": 34.67, 
      "degrees": 3, 
      "nlines": 104
     }
    }, 
    "avg_clustering": 0.7
   }, 
   {
    "total_lines": 283, 
    "deg_assort_coeff": -0.22273024167210984, 
    "density": 0.6190476190476191, 
    "scene": "3", 
    "total_degrees": 13, 
    "avg_shortest_path": 1.380952380952381, 
    "location": "France. KING LEWIS XI's palace.", 
    "act": "3", 
    "graph_img_f": "imgs/3henryvi_3_3.png", 
    "char_data": {
     "PRINCE EDWARD": {
      "ratio": 1.75, 
      "degrees": 4, 
      "nlines": 7
     }, 
     "QUEEN MARGARET": {
      "ratio": 18.75, 
      "degrees": 4, 
      "nlines": 75
     }, 
     "KING LEWIS XI": {
      "ratio": 14.4, 
      "degrees": 5, 
      "nlines": 72
     }, 
     "WARWICK": {
      "ratio": 18.6, 
      "degrees": 5, 
      "nlines": 93
     }, 
     "OXFORD": {
      "ratio": 6.33, 
      "degrees": 3, 
      "nlines": 19
     }, 
     "BONA": {
      "ratio": 3.33, 
      "degrees": 3, 
      "nlines": 10
     }, 
     "Post": {
      "ratio": 3.5, 
      "degrees": 2, 
      "nlines": 7
     }
    }, 
    "avg_clustering": 0.5619047619047619
   }
  ], 
  [
   {
    "total_lines": 155, 
    "deg_assort_coeff": -0.38024336592622782, 
    "density": 0.42857142857142855, 
    "scene": "1", 
    "total_degrees": 12, 
    "avg_shortest_path": 1.6428571428571428, 
    "location": "London. The palace.", 
    "act": "4", 
    "graph_img_f": "imgs/3henryvi_4_1.png", 
    "char_data": {
     "CLARENCE": {
      "ratio": 5.2, 
      "degrees": 5, 
      "nlines": 26
     }, 
     "MONTAGUE": {
      "ratio": 2.5, 
      "degrees": 2, 
      "nlines": 5
     }, 
     "KING EDWARD IV": {
      "ratio": 10.83, 
      "degrees": 6, 
      "nlines": 65
     }, 
     "QUEEN ELIZABETH": {
      "ratio": 8.0, 
      "degrees": 1, 
      "nlines": 8
     }, 
     "SOMERSET": {
      "ratio": 0.5, 
      "degrees": 2, 
      "nlines": 1
     }, 
     "HASTINGS": {
      "ratio": 2.67, 
      "degrees": 3, 
      "nlines": 8
     }, 
     "Post": {
      "ratio": 9.5, 
      "degrees": 2, 
      "nlines": 19
     }, 
     "GLOUCESTER": {
      "ratio": 7.67, 
      "degrees": 3, 
      "nlines": 23
     }
    }, 
    "avg_clustering": 0.625
   }, 
   {
    "total_lines": 32, 
    "deg_assort_coeff": -1, 
    "density": 1.0, 
    "scene": "2", 
    "total_degrees": 1, 
    "avg_shortest_path": 1.0, 
    "location": "A plain in Warwickshire.", 
    "act": "4", 
    "graph_img_f": "imgs/3henryvi_4_2.png", 
    "char_data": {
     "CLARENCE": {
      "ratio": 1.0, 
      "degrees": 1, 
      "nlines": 1
     }, 
     "WARWICK": {
      "ratio": 31.0, 
      "degrees": 1, 
      "nlines": 31
     }
    }, 
    "avg_clustering": 0.0
   }, 
   {
    "total_lines": 72, 
    "deg_assort_coeff": -0.25000000000000105, 
    "density": 0.47619047619047616, 
    "scene": "3", 
    "total_degrees": 10, 
    "avg_shortest_path": 1.619047619047619, 
    "location": "Edward's camp, near Warwick.", 
    "act": "4", 
    "graph_img_f": "imgs/3henryvi_4_3.png", 
    "char_data": {
     "Second Watchman": {
      "ratio": 2.5, 
      "degrees": 4, 
      "nlines": 10
     }, 
     "Third Watchman": {
      "ratio": 4.5, 
      "degrees": 2, 
      "nlines": 9
     }, 
     "First Watchman": {
      "ratio": 2.67, 
      "degrees": 3, 
      "nlines": 8
     }, 
     "KING EDWARD IV": {
      "ratio": 6.0, 
      "degrees": 2, 
      "nlines": 12
     }, 
     "WARWICK": {
      "ratio": 6.0, 
      "degrees": 5, 
      "nlines": 30
     }, 
     "OXFORD": {
      "ratio": 1.0, 
      "degrees": 2, 
      "nlines": 2
     }, 
     "SOMERSET": {
      "ratio": 0.5, 
      "degrees": 2, 
      "nlines": 1
     }
    }, 
    "avg_clustering": 0.780952380952381
   }, 
   {
    "total_lines": 36, 
    "deg_assort_coeff": -1, 
    "density": 1.0, 
    "scene": "4", 
    "total_degrees": 1, 
    "avg_shortest_path": 1.0, 
    "location": "London. The palace.", 
    "act": "4", 
    "graph_img_f": "imgs/3henryvi_4_4.png", 
    "char_data": {
     "QUEEN ELIZABETH": {
      "ratio": 29.0, 
      "degrees": 1, 
      "nlines": 29
     }, 
     "RIVERS": {
      "ratio": 7.0, 
      "degrees": 1, 
      "nlines": 7
     }
    }, 
    "avg_clustering": 0.0
   }, 
   {
    "total_lines": 32, 
    "deg_assort_coeff": -0.63716814159292134, 
    "density": 0.8333333333333334, 
    "scene": "5", 
    "total_degrees": 5, 
    "avg_shortest_path": 1.1666666666666667, 
    "location": "A park near Middleham Castle In Yorkshire.", 
    "act": "4", 
    "graph_img_f": "imgs/3henryvi_4_5.png", 
    "char_data": {
     "KING EDWARD IV": {
      "ratio": 3.0, 
      "degrees": 3, 
      "nlines": 9
     }, 
     "Huntsman": {
      "ratio": 1.0, 
      "degrees": 2, 
      "nlines": 2
     }, 
     "GLOUCESTER": {
      "ratio": 6.33, 
      "degrees": 3, 
      "nlines": 19
     }, 
     "HASTINGS": {
      "ratio": 1.0, 
      "degrees": 2, 
      "nlines": 2
     }
    }, 
    "avg_clustering": 0.8333333333333333
   }, 
   {
    "total_lines": 107, 
    "deg_assort_coeff": -0.27198829458624613, 
    "density": 0.38095238095238093, 
    "scene": "6", 
    "total_degrees": 8, 
    "avg_shortest_path": 1.8095238095238095, 
    "location": "London. The Tower.", 
    "act": "4", 
    "graph_img_f": "imgs/3henryvi_4_6.png", 
    "char_data": {
     "CLARENCE": {
      "ratio": 4.5, 
      "degrees": 2, 
      "nlines": 9
     }, 
     "KING HENRY VI": {
      "ratio": 12.25, 
      "degrees": 4, 
      "nlines": 49
     }, 
     "Lieutenant": {
      "ratio": 3.0, 
      "degrees": 1, 
      "nlines": 3
     }, 
     "WARWICK": {
      "ratio": 5.75, 
      "degrees": 4, 
      "nlines": 23
     }, 
     "OXFORD": {
      "ratio": 2.0, 
      "degrees": 1, 
      "nlines": 2
     }, 
     "Post": {
      "ratio": 7.0, 
      "degrees": 1, 
      "nlines": 7
     }, 
     "SOMERSET": {
      "ratio": 4.67, 
      "degrees": 3, 
      "nlines": 14
     }
    }, 
    "avg_clustering": 0.2857142857142857
   }, 
   {
    "total_lines": 96, 
    "deg_assort_coeff": -0.27513728460518933, 
    "density": 0.6190476190476191, 
    "scene": "7", 
    "total_degrees": 13, 
    "avg_shortest_path": 1.380952380952381, 
    "location": "Before York.", 
    "act": "4", 
    "graph_img_f": "imgs/3henryvi_4_7.png", 
    "char_data": {
     "All": {
      "ratio": 0.5, 
      "degrees": 2, 
      "nlines": 1
     }, 
     "KING EDWARD IV": {
      "ratio": 9.2, 
      "degrees": 5, 
      "nlines": 46
     }, 
     "MONTAGUE": {
      "ratio": 3.2, 
      "degrees": 5, 
      "nlines": 16
     }, 
     "Soldier": {
      "ratio": 1.0, 
      "degrees": 2, 
      "nlines": 2
     }, 
     "HASTINGS": {
      "ratio": 2.6, 
      "degrees": 5, 
      "nlines": 13
     }, 
     "Mayor": {
      "ratio": 2.0, 
      "degrees": 3, 
      "nlines": 6
     }, 
     "GLOUCESTER": {
      "ratio": 3.0, 
      "degrees": 4, 
      "nlines": 12
     }
    }, 
    "avg_clustering": 0.7904761904761904
   }, 
   {
    "total_lines": 69, 
    "deg_assort_coeff": -0.21780604133545226, 
    "density": 0.32142857142857145, 
    "scene": "8", 
    "total_degrees": 9, 
    "avg_shortest_path": 2.142857142857143, 
    "location": "London. The palace.", 
    "act": "4", 
    "graph_img_f": "imgs/3henryvi_4_8.png", 
    "char_data": {
     "CLARENCE": {
      "ratio": 1.5, 
      "degrees": 2, 
      "nlines": 3
     }, 
     "KING HENRY VI": {
      "ratio": 4.6, 
      "degrees": 5, 
      "nlines": 23
     }, 
     "MONTAGUE": {
      "ratio": 0.5, 
      "degrees": 2, 
      "nlines": 1
     }, 
     "KING EDWARD IV": {
      "ratio": 5.5, 
      "degrees": 2, 
      "nlines": 11
     }, 
     "WARWICK": {
      "ratio": 11.5, 
      "degrees": 2, 
      "nlines": 23
     }, 
     "OXFORD": {
      "ratio": 0.5, 
      "degrees": 2, 
      "nlines": 1
     }, 
     "EXETER": {
      "ratio": 1.5, 
      "degrees": 2, 
      "nlines": 3
     }, 
     "GLOUCESTER": {
      "ratio": 4.0, 
      "degrees": 1, 
      "nlines": 4
     }
    }, 
    "avg_clustering": 0.525
   }
  ], 
  [
   {
    "total_lines": 125, 
    "deg_assort_coeff": -0.65827828457586213, 
    "density": 0.3333333333333333, 
    "scene": "1", 
    "total_degrees": 15, 
    "avg_shortest_path": 1.7333333333333334, 
    "location": "Coventry.", 
    "act": "5", 
    "graph_img_f": "imgs/3henryvi_5_1.png", 
    "char_data": {
     "CLARENCE": {
      "ratio": 11.5, 
      "degrees": 2, 
      "nlines": 23
     }, 
     "Second Messenger": {
      "ratio": 2.0, 
      "degrees": 1, 
      "nlines": 2
     }, 
     "First Messenger": {
      "ratio": 1.0, 
      "degrees": 1, 
      "nlines": 1
     }, 
     "MONTAGUE": {
      "ratio": 1.0, 
      "degrees": 2, 
      "nlines": 2
     }, 
     "KING EDWARD IV": {
      "ratio": 7.5, 
      "degrees": 4, 
      "nlines": 30
     }, 
     "EDWARD": {
      "ratio": 1.0, 
      "degrees": 1, 
      "nlines": 1
     }, 
     "WARWICK": {
      "ratio": 4.38, 
      "degrees": 8, 
      "nlines": 35
     }, 
     "OXFORD": {
      "ratio": 1.0, 
      "degrees": 2, 
      "nlines": 2
     }, 
     "SOMERSET": {
      "ratio": 3.0, 
      "degrees": 3, 
      "nlines": 9
     }, 
     "GLOUCESTER": {
      "ratio": 3.33, 
      "degrees": 6, 
      "nlines": 20
     }
    }, 
    "avg_clustering": 0.5214285714285715
   }, 
   {
    "total_lines": 54, 
    "deg_assort_coeff": -0.80000000000000004, 
    "density": 0.5, 
    "scene": "2", 
    "total_degrees": 3, 
    "avg_shortest_path": 1.5, 
    "location": "A field of battle near Barnet.", 
    "act": "5", 
    "graph_img_f": "imgs/3henryvi_5_2.png", 
    "char_data": {
     "OXFORD": {
      "ratio": 2.0, 
      "degrees": 1, 
      "nlines": 2
     }, 
     "KING EDWARD IV": {
      "ratio": 5.0, 
      "degrees": 1, 
      "nlines": 5
     }, 
     "SOMERSET": {
      "ratio": 12.0, 
      "degrees": 1, 
      "nlines": 12
     }, 
     "WARWICK": {
      "ratio": 11.67, 
      "degrees": 3, 
      "nlines": 35
     }
    }, 
    "avg_clustering": 0.0
   }, 
   {
    "total_lines": 25, 
    "deg_assort_coeff": -1, 
    "density": 1.0, 
    "scene": "3", 
    "total_degrees": 3, 
    "avg_shortest_path": 1.0, 
    "location": "Another part of the field.", 
    "act": "5", 
    "graph_img_f": "imgs/3henryvi_5_3.png", 
    "char_data": {
     "KING EDWARD IV": {
      "ratio": 8.5, 
      "degrees": 2, 
      "nlines": 17
     }, 
     "CLARENCE": {
      "ratio": 2.0, 
      "degrees": 2, 
      "nlines": 4
     }, 
     "GLOUCESTER": {
      "ratio": 2.0, 
      "degrees": 2, 
      "nlines": 4
     }
    }, 
    "avg_clustering": 1.0
   }, 
   {
    "total_lines": 85, 
    "deg_assort_coeff": -0.46411483253588515, 
    "density": 0.6, 
    "scene": "4", 
    "total_degrees": 9, 
    "avg_shortest_path": 1.4, 
    "location": "Plains near Tewksbury.", 
    "act": "5", 
    "graph_img_f": "imgs/3henryvi_5_4.png", 
    "char_data": {
     "PRINCE EDWARD": {
      "ratio": 4.33, 
      "degrees": 3, 
      "nlines": 13
     }, 
     "QUEEN MARGARET": {
      "ratio": 12.75, 
      "degrees": 4, 
      "nlines": 51
     }, 
     "KING EDWARD IV": {
      "ratio": 3.0, 
      "degrees": 2, 
      "nlines": 6
     }, 
     "Messenger": {
      "ratio": 1.0, 
      "degrees": 2, 
      "nlines": 2
     }, 
     "OXFORD": {
      "ratio": 1.8, 
      "degrees": 5, 
      "nlines": 9
     }, 
     "SOMERSET": {
      "ratio": 2.0, 
      "degrees": 2, 
      "nlines": 4
     }
    }, 
    "avg_clustering": 0.7611111111111111
   }, 
   {
    "total_lines": 99, 
    "deg_assort_coeff": -0.029966379184330261, 
    "density": 0.6190476190476191, 
    "scene": "5", 
    "total_degrees": 13, 
    "avg_shortest_path": 1.380952380952381, 
    "location": "Another part of the field.", 
    "act": "5", 
    "graph_img_f": "imgs/3henryvi_5_5.png", 
    "char_data": {
     "PRINCE EDWARD": {
      "ratio": 3.25, 
      "degrees": 4, 
      "nlines": 13
     }, 
     "CLARENCE": {
      "ratio": 2.0, 
      "degrees": 4, 
      "nlines": 8
     }, 
     "QUEEN MARGARET": {
      "ratio": 6.8, 
      "degrees": 5, 
      "nlines": 34
     }, 
     "KING EDWARD IV": {
      "ratio": 5.0, 
      "degrees": 5, 
      "nlines": 25
     }, 
     "OXFORD": {
      "ratio": 0.5, 
      "degrees": 2, 
      "nlines": 1
     }, 
     "SOMERSET": {
      "ratio": 1.0, 
      "degrees": 2, 
      "nlines": 2
     }, 
     "GLOUCESTER": {
      "ratio": 4.0, 
      "degrees": 4, 
      "nlines": 16
     }
    }, 
    "avg_clustering": 0.6
   }, 
   {
    "total_lines": 98, 
    "deg_assort_coeff": -1, 
    "density": 1.0, 
    "scene": "6", 
    "total_degrees": 1, 
    "avg_shortest_path": 1.0, 
    "location": "London. The Tower.", 
    "act": "5", 
    "graph_img_f": "imgs/3henryvi_5_6.png", 
    "char_data": {
     "GLOUCESTER": {
      "ratio": 48.0, 
      "degrees": 1, 
      "nlines": 48
     }, 
     "KING HENRY VI": {
      "ratio": 50.0, 
      "degrees": 1, 
      "nlines": 50
     }
    }, 
    "avg_clustering": 0.0
   }, 
   {
    "total_lines": 48, 
    "deg_assort_coeff": 0.0, 
    "density": 0.6666666666666666, 
    "scene": "7", 
    "total_degrees": 4, 
    "avg_shortest_path": 1.3333333333333333, 
    "location": "London. The palace.", 
    "act": "5", 
    "graph_img_f": "imgs/3henryvi_5_7.png", 
    "char_data": {
     "KING EDWARD IV": {
      "ratio": 16.0, 
      "degrees": 2, 
      "nlines": 32
     }, 
     "GLOUCESTER": {
      "ratio": 4.5, 
      "degrees": 2, 
      "nlines": 9
     }, 
     "QUEEN ELIZABETH": {
      "ratio": 0.5, 
      "degrees": 2, 
      "nlines": 1
     }, 
     "CLARENCE": {
      "ratio": 3.0, 
      "degrees": 2, 
      "nlines": 6
     }
    }, 
    "avg_clustering": 0.0
   }
  ]
 ], 
 "characters": [
  "WARWICK", 
  "YORK", 
  "EDWARD", 
  "MONTAGUE", 
  "RICHARD", 
  "NORFOLK", 
  "KING HENRY VI", 
  "NORTHUMBERLAND", 
  "CLIFFORD", 
  "WESTMORELAND", 
  "EXETER", 
  "QUEEN MARGARET", 
  "PRINCE EDWARD", 
  "Messenger", 
  "JOHN MORTIMER", 
  "RUTLAND", 
  "Tutor", 
  "PRINCE", 
  "GEORGE", 
  "Son", 
  "Father", 
  "First Keeper", 
  "Second Keeper", 
  "KING EDWARD IV", 
  "GLOUCESTER", 
  "CLARENCE", 
  "LADY GREY", 
  "Nobleman", 
  "KING LEWIS XI", 
  "OXFORD", 
  "BONA", 
  "Post", 
  "SOMERSET", 
  "HASTINGS", 
  "QUEEN ELIZABETH", 
  "First Watchman", 
  "Second Watchman", 
  "Third Watchman", 
  "RIVERS", 
  "Huntsman", 
  "Lieutenant", 
  "Mayor", 
  "Soldier", 
  "All", 
  "First Messenger", 
  "Second Messenger"
 ], 
 "year": "1590-91 / 1594?", 
 "char_data": {
  "Nobleman": {
   "ratio": 2.0, 
   "degrees": 1, 
   "nlines": 2, 
   "order_app": 27
  }, 
  "RICHARD": {
   "ratio": 13.33, 
   "degrees": 12, 
   "nlines": 160, 
   "order_app": 4
  }, 
  "Post": {
   "ratio": 6.6, 
   "degrees": 5, 
   "nlines": 33, 
   "order_app": 31
  }, 
  "Father": {
   "ratio": 14.0, 
   "degrees": 2, 
   "nlines": 28, 
   "order_app": 20
  }, 
  "MONTAGUE": {
   "ratio": 3.0, 
   "degrees": 13, 
   "nlines": 39, 
   "order_app": 3
  }, 
  "Tutor": {
   "ratio": 4.0, 
   "degrees": 1, 
   "nlines": 4, 
   "order_app": 16
  }, 
  "Messenger": {
   "ratio": 5.14, 
   "degrees": 7, 
   "nlines": 36, 
   "order_app": 13
  }, 
  "WARWICK": {
   "ratio": 17.5, 
   "degrees": 26, 
   "nlines": 455, 
   "order_app": 0
  }, 
  "RUTLAND": {
   "ratio": 26.0, 
   "degrees": 1, 
   "nlines": 26, 
   "order_app": 15
  }, 
  "First Watchman": {
   "ratio": 2.67, 
   "degrees": 3, 
   "nlines": 8, 
   "order_app": 35
  }, 
  "Lieutenant": {
   "ratio": 3.0, 
   "degrees": 1, 
   "nlines": 3, 
   "order_app": 40
  }, 
  "PRINCE EDWARD": {
   "ratio": 3.83, 
   "degrees": 12, 
   "nlines": 46, 
   "order_app": 12
  }, 
  "QUEEN ELIZABETH": {
   "ratio": 9.5, 
   "degrees": 4, 
   "nlines": 38, 
   "order_app": 34
  }, 
  "KING HENRY VI": {
   "ratio": 18.65, 
   "degrees": 20, 
   "nlines": 373, 
   "order_app": 6
  }, 
  "Huntsman": {
   "ratio": 1.0, 
   "degrees": 2, 
   "nlines": 2, 
   "order_app": 39
  }, 
  "NORTHUMBERLAND": {
   "ratio": 3.88, 
   "degrees": 8, 
   "nlines": 31, 
   "order_app": 7
  }, 
  "First Messenger": {
   "ratio": 1.0, 
   "degrees": 1, 
   "nlines": 1, 
   "order_app": 44
  }, 
  "PRINCE": {
   "ratio": 1.5, 
   "degrees": 2, 
   "nlines": 3, 
   "order_app": 17
  }, 
  "KING EDWARD IV": {
   "ratio": 18.65, 
   "degrees": 17, 
   "nlines": 317, 
   "order_app": 23
  }, 
  "WESTMORELAND": {
   "ratio": 2.75, 
   "degrees": 4, 
   "nlines": 11, 
   "order_app": 9
  }, 
  "KING LEWIS XI": {
   "ratio": 14.4, 
   "degrees": 5, 
   "nlines": 72, 
   "order_app": 28
  }, 
  "BONA": {
   "ratio": 3.33, 
   "degrees": 3, 
   "nlines": 10, 
   "order_app": 30
  }, 
  "EXETER": {
   "ratio": 4.0, 
   "degrees": 5, 
   "nlines": 20, 
   "order_app": 10
  }, 
  "GLOUCESTER": {
   "ratio": 17.27, 
   "degrees": 15, 
   "nlines": 259, 
   "order_app": 24
  }, 
  "NORFOLK": {
   "ratio": 0.75, 
   "degrees": 4, 
   "nlines": 3, 
   "order_app": 5
  }, 
  "CLARENCE": {
   "ratio": 8.55, 
   "degrees": 11, 
   "nlines": 94, 
   "order_app": 25
  }, 
  "LADY GREY": {
   "ratio": 12.0, 
   "degrees": 3, 
   "nlines": 36, 
   "order_app": 26
  }, 
  "Second Watchman": {
   "ratio": 2.5, 
   "degrees": 4, 
   "nlines": 10, 
   "order_app": 36
  }, 
  "Third Watchman": {
   "ratio": 4.5, 
   "degrees": 2, 
   "nlines": 9, 
   "order_app": 37
  }, 
  "RIVERS": {
   "ratio": 7.0, 
   "degrees": 1, 
   "nlines": 7, 
   "order_app": 38
  }, 
  "First Keeper": {
   "ratio": 9.0, 
   "degrees": 2, 
   "nlines": 18, 
   "order_app": 21
  }, 
  "Soldier": {
   "ratio": 1.0, 
   "degrees": 2, 
   "nlines": 2, 
   "order_app": 42
  }, 
  "JOHN MORTIMER": {
   "ratio": 0.5, 
   "degrees": 2, 
   "nlines": 1, 
   "order_app": 14
  }, 
  "OXFORD": {
   "ratio": 3.8, 
   "degrees": 10, 
   "nlines": 38, 
   "order_app": 29
  }, 
  "GEORGE": {
   "ratio": 7.33, 
   "degrees": 3, 
   "nlines": 22, 
   "order_app": 18
  }, 
  "CLIFFORD": {
   "ratio": 12.42, 
   "degrees": 12, 
   "nlines": 149, 
   "order_app": 8
  }, 
  "All": {
   "ratio": 0.5, 
   "degrees": 2, 
   "nlines": 1, 
   "order_app": 43
  }, 
  "Second Messenger": {
   "ratio": 2.0, 
   "degrees": 1, 
   "nlines": 2, 
   "order_app": 45
  }, 
  "QUEEN MARGARET": {
   "ratio": 17.94, 
   "degrees": 16, 
   "nlines": 287, 
   "order_app": 11
  }, 
  "SOMERSET": {
   "ratio": 5.38, 
   "degrees": 8, 
   "nlines": 43, 
   "order_app": 32
  }, 
  "Son": {
   "ratio": 11.5, 
   "degrees": 2, 
   "nlines": 23, 
   "order_app": 19
  }, 
  "EDWARD": {
   "ratio": 13.4, 
   "degrees": 10, 
   "nlines": 134, 
   "order_app": 2
  }, 
  "HASTINGS": {
   "ratio": 3.83, 
   "degrees": 6, 
   "nlines": 23, 
   "order_app": 33
  }, 
  "Second Keeper": {
   "ratio": 7.5, 
   "degrees": 2, 
   "nlines": 15, 
   "order_app": 22
  }, 
  "Mayor": {
   "ratio": 2.0, 
   "degrees": 3, 
   "nlines": 6, 
   "order_app": 41
  }, 
  "YORK": {
   "ratio": 14.75, 
   "degrees": 12, 
   "nlines": 177, 
   "order_app": 1
  }
 }, 
 "type": "History"
}